{
  "name": "@paulmillr/micro-key-producer",
  "version": "0.8.0",
  "exports": {
    ".": "./src/index.ts",
    "./bls.js": "./src/bls.ts",
    "./convert.js": "./src/convert.ts",
    "./ipns.js": "./src/ipns.ts",
    "./otp.js": "./src/otp.ts",
    "./password.js": "./src/password.ts",
    "./pgp.js": "./src/pgp.ts",
    "./slip10.js": "./src/slip10.ts",
    "./ssh.js": "./src/ssh.ts",
    "./tor.js": "./src/tor.ts",
    "./utils.js": "./src/utils.ts"
  },
  "imports": {
    "@noble/ciphers": "jsr:@noble/ciphers@^2.0.0",
    "@noble/curves": "jsr:@noble/curves@^2.0.0",
    "@noble/hashes": "jsr:@noble/hashes@^2.0.0",
    "@scure/base": "jsr:@scure/base@^2.0.0",
    "micro-packed": "jsr:@paulmillr/micro-packed@^0.8.0"
  },
  "publish": {
    "include": [
      "src",
      "jsr.json",
      "LICENSE",
      "README.md"
    ]
  },
  "license": "MIT"
}
